setup.py
asynctelegraph/__init__.py
asynctelegraph/client.py
asynctelegraph/exceptions.py
asynctelegraph/html_parser.py
asynctelegraph/types.py
asynctelegraph.egg-info/PKG-INFO
asynctelegraph.egg-info/SOURCES.txt
asynctelegraph.egg-info/dependency_links.txt
asynctelegraph.egg-info/requires.txt
asynctelegraph.egg-info/top_level.txt