Metadata-Version: 1.1
Name: asynctelegraph
Version: 0.1.1
Summary: Asynchronous telegraph API wrapper
Home-page: https://github.com/
Author: Artem Burenin
Author-email: burenotti@gmail.com
License: MIT
Platform: UNKNOWN
Classifier: License :: OSI Approved :: MIT License
Classifier: Programming Language :: Python :: 3
Classifier: Programming Language :: Python :: 3.7
